hikka_filters/__init__.py
hikka_filters/filters.py
hikka_filters-0.2.0.dist-info/LICENSE
hikka_filters-0.2.0.dist-info/METADATA
hikka_filters-0.2.0.dist-info/WHEEL
hikka_filters-0.2.0.dist-info/top_level.txt
hikka_filters-0.2.0.dist-info/RECORD
